depscanner/__init__.py
depscanner/depscanner.py
depscanner-0.4.dist-info/LICENSE
depscanner-0.4.dist-info/METADATA
depscanner-0.4.dist-info/WHEEL
depscanner-0.4.dist-info/top_level.txt
depscanner-0.4.dist-info/RECORD
