Metadata-Version: 2.1
Name: depscanner
Version: 0.4
Summary: Python Dependency Scanner
Author: nickdecodes
Author-email: nickdecodes <nickdecodes@163.com>
Project-URL: Documentation, http://python-depscanner.readthedocs.io
Project-URL: Source, https://github.com/nickdecodes/python-depscanner
Keywords: depscanner,python,dependency
Requires-Python: >=3.6
License-File: LICENSE
Requires-Dist: requests
Requires-Dist: aiohttp
Requires-Dist: stdlib-list
Requires-Dist: twine
